deaddrops/__init__.py
deaddrops/database.py
deaddrops/submit.py
deaddrops-1.1.2.dist-info/METADATA
deaddrops-1.1.2.dist-info/WHEEL
deaddrops-1.1.2.dist-info/top_level.txt
deaddrops-1.1.2.dist-info/RECORD
