Metadata-Version: 2.1
Name: deaddrops
Version: 1.1.2
Summary: A simple python library to interact with the dead drops official website.
Author: Darnethal0z
Project-URL: Homepage, https://github.com/Darnethal0z/deaddrops
Project-URL: Bug Tracker, https://github.com/Darnethal0z/deaddrops/issues
Classifier: Development Status :: 5 - Production/Stable
Classifier: Intended Audience :: Developers
Classifier: Programming Language :: Python :: 3
Classifier: Topic :: Internet
Requires-Dist: beautifulsoup4
Requires-Dist: requests
Requires-Dist: pillow
Requires-Dist: pycountry
